{
  "_class": "shapePath",
  "booleanOperation": -1,
  "do_objectID": "157E49C4-9E75-430C-99DF-4B3864412138",
  "edited": true,
  "exportOptions": {
    "_class": "exportOptions",
    "exportFormats": [
    ],
    "includedLayerIds": [
    ],
    "layerOptions": 0,
    "shouldTrim": false
  },
  "frame": {
    "_class": "rect",
    "constrainProportions": false,
    "height": 26.00000000000002,
    "width": 26,
    "x": 6,
    "y": 7.999999999999999
  },
  "isFlippedHorizontal": false,
  "isFlippedVertical": false,
  "isLocked": false,
  "isVisible": true,
  "layerListExpandedType": 0,
  "name": "Path",
  "nameIsFixed": false,
  "path": {
    "_class": "path",
    "isClosed": true,
    "pointRadiusBehaviour": 1,
    "points": [
      {
        "_class": "curvePoint",
        "cornerRadius": 0,
        "curveFrom": "{0.22430769230769615, 1}",
        "curveMode": 2,
        "curveTo": "{0.7756923076923038, 1}",
        "hasCurveFrom": true,
        "hasCurveTo": true,
        "point": "{0.5, 1}"
      },
      {
        "_class": "curvePoint",
        "cornerRadius": 0,
        "curveFrom": "{0, 0.22426923076923141}",
        "curveMode": 2,
        "curveTo": "{0, 0.77573076923076933}",
        "hasCurveFrom": true,
        "hasCurveTo": true,
        "point": "{0, 0.50000000000000022}"
      },
      {
        "_class": "curvePoint",
        "cornerRadius": 0,
        "curveFrom": "{0.7756923076923038, 0}",
        "curveMode": 2,
        "curveTo": "{0.22430769230769615, 0}",
        "hasCurveFrom": true,
        "hasCurveTo": true,
        "point": "{0.5, 0}"
      },
      {
        "_class": "curvePoint",
        "cornerRadius": 0,
        "curveFrom": "{1, 0.77573076923076933}",
        "curveMode": 2,
        "curveTo": "{1, 0.22426923076923141}",
        "hasCurveFrom": true,
        "hasCurveTo": true,
        "point": "{1, 0.50000000000000022}"
      }
    ]
  },
  "resizingConstraint": 63,
  "resizingType": 0,
  "rotation": 0,
  "shouldBreakMaskChain": false
}