{
  "_class": "shapePath",
  "booleanOperation": -1,
  "do_objectID": "082C0030-B0AB-42B5-AA24-597CF1434903",
  "edited": true,
  "exportOptions": {
    "_class": "exportOptions",
    "exportFormats": [
    ],
    "includedLayerIds": [
    ],
    "layerOptions": 0,
    "shouldTrim": false
  },
  "frame": {
    "_class": "rect",
    "constrainProportions": false,
    "height": 20,
    "width": 52.72290176525787,
    "x": 1.276098234742397,
    "y": 0
  },
  "isFlippedHorizontal": false,
  "isFlippedVertical": false,
  "isLocked": false,
  "isVisible": true,
  "layerListExpandedType": 0,
  "name": "Path",
  "nameIsFixed": false,
  "path": {
    "_class": "path",
    "isClosed": true,
    "pointRadiusBehaviour": 1,
    "points": [
      {
        "_class": "curvePoint",
        "cornerRadius": 0,
        "curveFrom": "{0.98103291043326157, 1}",
        "curveMode": 3,
        "curveTo": "{0.99150274387409532, 1}",
        "hasCurveFrom": true,
        "hasCurveTo": true,
        "point": "{0.98103291043326157, 1}"
      },
      {
        "_class": "curvePoint",
        "cornerRadius": 0,
        "curveFrom": "{0.78089218132503513, 1}",
        "curveMode": 3,
        "curveTo": "{0.79136201476587675, 1}",
        "hasCurveFrom": true,
        "hasCurveTo": true,
        "point": "{0.79136201476587675, 1}"
      },
      {
        "_class": "curvePoint",
        "cornerRadius": 0,
        "curveFrom": "{0.77239492519913833, 0.9224}",
        "curveMode": 2,
        "curveTo": "{0.77239492519913833, 0.97760000000000002}",
        "hasCurveFrom": true,
        "hasCurveTo": true,
        "point": "{0.77239492519913833, 0.94999999999999996}"
      },
      {
        "_class": "curvePoint",
        "cornerRadius": 0,
        "curveFrom": "{0.79136201476587675, 0.90000000000000002}",
        "curveMode": 4,
        "curveTo": "{0.78089218132503513, 0.90000000000000002}",
        "hasCurveFrom": true,
        "hasCurveTo": true,
        "point": "{0.79136201476587675, 0.90000000000000002}"
      },
      {
        "_class": "curvePoint",
        "cornerRadius": 0,
        "curveFrom": "{0.85981424101223392, 0.41909999999999747}",
        "curveMode": 4,
        "curveTo": "{0.93006834076743694, 0.90000000000000002}",
        "hasCurveFrom": true,
        "hasCurveTo": true,
        "point": "{0.93006834076743694, 0.90000000000000002}"
      },
      {
        "_class": "curvePoint",
        "cornerRadius": 0,
        "curveFrom": "{0.28200082445111496, 0.10000000000000001}",
        "curveMode": 2,
        "curveTo": "{0.68537391826693828, 0.10000000000000001}",
        "hasCurveFrom": true,
        "hasCurveTo": true,
        "point": "{0.48790754878762221, 0.10000000000000001}"
      },
      {
        "_class": "curvePoint",
        "cornerRadius": 0,
        "curveFrom": "{0.03375955620163764, 0.98829999999999996}",
        "curveMode": 3,
        "curveTo": "{0.10078925073049351, 0.44644999999999851}",
        "hasCurveFrom": true,
        "hasCurveTo": true,
        "point": "{0.037002928517555232, 0.96204999999999996}"
      },
      {
        "_class": "curvePoint",
        "cornerRadius": 0,
        "curveFrom": "{0.0031277065513591754, 0.98550000000000004}",
        "curveMode": 2,
        "curveTo": "{0.023119018954703235, 1.0026999999999999}",
        "hasCurveFrom": true,
        "hasCurveTo": true,
        "point": "{0.013085428573898583, 0.99404999999999999}"
      },
      {
        "_class": "curvePoint",
        "cornerRadius": 0,
        "curveFrom": "{0.069834960557575168, 0.37414999999999748}",
        "curveMode": 3,
        "curveTo": "{-0.0023158481542997012, 0.95724999999999993}",
        "hasCurveFrom": true,
        "hasCurveTo": true,
        "point": "{0.00094649125117988358, 0.93104999999999993}"
      },
      {
        "_class": "curvePoint",
        "cornerRadius": 0,
        "curveFrom": "{0.69791116447055435, 0}",
        "curveMode": 3,
        "curveTo": "{0.26553739070718596, 0}",
        "hasCurveFrom": true,
        "hasCurveTo": true,
        "point": "{0.48790754878762221, 0}"
      },
      {
        "_class": "curvePoint",
        "cornerRadius": 0,
        "curveFrom": "{0.96206582086652304, 0.84009999999999996}",
        "curveMode": 4,
        "curveTo": "{0.88397831312025688, 0.33389999999999997}",
        "hasCurveFrom": true,
        "hasCurveTo": true,
        "point": "{0.96206582086652304, 0.84009999999999996}"
      },
      {
        "_class": "curvePoint",
        "cornerRadius": 0,
        "curveFrom": "{0.96206582086652304, 0.42239999999999905}",
        "curveMode": 4,
        "curveTo": "{0.96206582086652304, 0.45000000000000001}",
        "hasCurveFrom": true,
        "hasCurveTo": true,
        "point": "{0.96206582086652304, 0.45000000000000001}"
      },
      {
        "_class": "curvePoint",
        "cornerRadius": 0,
        "curveFrom": "{0.99150274387409532, 0.40000000000000002}",
        "curveMode": 2,
        "curveTo": "{0.97056307699241984, 0.40000000000000002}",
        "hasCurveFrom": true,
        "hasCurveTo": true,
        "point": "{0.98103291043326157, 0.40000000000000002}"
      },
      {
        "_class": "curvePoint",
        "cornerRadius": 0,
        "curveFrom": "{1, 0.45000000000000001}",
        "curveMode": 4,
        "curveTo": "{1, 0.42239999999999905}",
        "hasCurveFrom": true,
        "hasCurveTo": true,
        "point": "{1, 0.45000000000000001}"
      },
      {
        "_class": "curvePoint",
        "cornerRadius": 0,
        "curveFrom": "{1, 0.97760000000000002}",
        "curveMode": 4,
        "curveTo": "{1, 0.94999999999999996}",
        "hasCurveFrom": true,
        "hasCurveTo": true,
        "point": "{1, 0.94999999999999996}"
      }
    ]
  },
  "resizingConstraint": 63,
  "resizingType": 0,
  "rotation": 0,
  "shouldBreakMaskChain": false
}